fast_jsonl/__init__.py
fast_jsonl/cache.py
fast_jsonl/cli.py
fast_jsonl/constants.py
fast_jsonl/lock.py
fast_jsonl/pathing.py
fast_jsonl/reader.py
fast_jsonl-0.1.0.dist-info/LICENSE
fast_jsonl-0.1.0.dist-info/METADATA
fast_jsonl-0.1.0.dist-info/WHEEL
fast_jsonl-0.1.0.dist-info/entry_points.txt
fast_jsonl-0.1.0.dist-info/top_level.txt
fast_jsonl-0.1.0.dist-info/RECORD
