Metadata-Version: 2.1
Name: fast-jsonl
Version: 0.1.0
Summary: A simple JSONL reader that caches line byte positions for fast loading.
Author-email: Mathew Huerta-Enochian <mathewhe@gmail.com>
Maintainer-email: Mathew Huerta-Enochian <mathewhe@gmail.com>
Project-URL: repository, https://github.com/mathewhuen/fast-jsonl
Project-URL: changelog, https://github.com/mathewhuen/fast-jsonl/blob/main/CHANGELOG.md
Classifier: License :: OSI Approved :: Apache Software License
Classifier: Operating System :: OS Independent
Classifier: Intended Audience :: Developers
Classifier: Intended Audience :: Science/Research
Classifier: Programming Language :: Python :: 3
Classifier: Programming Language :: Python :: 3.8
Classifier: Programming Language :: Python :: 3.9
Classifier: Programming Language :: Python :: 3.10
Classifier: Programming Language :: Python :: 3.11
Classifier: Programming Language :: Python :: 3.12
Requires-Python: >=3.8.0
License-File: LICENSE
Requires-Dist: filelock
Provides-Extra: dev
Requires-Dist: pytest ; extra == 'dev'
Requires-Dist: black ; extra == 'dev'
Requires-Dist: sphinx ; extra == 'dev'
Requires-Dist: sphinx-copybutton ; extra == 'dev'
Requires-Dist: pydata-sphinx-theme ; extra == 'dev'
Requires-Dist: myst-parser ; extra == 'dev'
